app_commands/__init__.py
app_commands/base.py
app_commands/commands.py
app_commands/handlers.py
app_commands/lifespan.py
app_commands/termcolors.py
app_commands-0.1.0.dist-info/AUTHORS.rst
app_commands-0.1.0.dist-info/LICENSE
app_commands-0.1.0.dist-info/METADATA
app_commands-0.1.0.dist-info/WHEEL
app_commands-0.1.0.dist-info/top_level.txt
app_commands-0.1.0.dist-info/RECORD
