Metadata-Version: 2.1
Name: app-commands
Version: 0.1.0
Summary: CLI commands utility with ASGI lifespan and healthcheck support.
Home-page: https://github.com/ryananguiano/app-commands
Author: Ryan Anguiano
Author-email: ryan.anguiano@gmail.com
License: MIT license
Keywords: app_commands
Classifier: Development Status :: 2 - Pre-Alpha
Classifier: Intended Audience :: Developers
Classifier: License :: OSI Approved :: MIT License
Classifier: Natural Language :: English
Classifier: Programming Language :: Python :: 3
Classifier: Programming Language :: Python :: 3.7
Classifier: Programming Language :: Python :: 3.8
Classifier: Programming Language :: Python :: 3.9
Classifier: Programming Language :: Python :: 3.10
Requires-Python: >=3.7
License-File: LICENSE
License-File: AUTHORS.rst
Requires-Dist: Click (>=7.0)
Provides-Extra: healthcheck
Requires-Dist: aiohttp ; extra == 'healthcheck'
Requires-Dist: aio-tiny-healthcheck ; extra == 'healthcheck'
